cr_kyoushi/statemachines/__init__.py
cr_kyoushi/statemachines/aecid_attacker/__init__.py
cr_kyoushi/statemachines/aecid_attacker/actions.py
cr_kyoushi/statemachines/aecid_attacker/config.py
cr_kyoushi/statemachines/aecid_attacker/context.py
cr_kyoushi/statemachines/aecid_attacker/expect.py
cr_kyoushi/statemachines/aecid_attacker/sm.py
cr_kyoushi/statemachines/aecid_attacker/sm.smcat
cr_kyoushi/statemachines/aecid_attacker/states.py
cr_kyoushi/statemachines/beta_user/__init__.py
cr_kyoushi/statemachines/beta_user/actions.py
cr_kyoushi/statemachines/beta_user/config.py
cr_kyoushi/statemachines/beta_user/context.py
cr_kyoushi/statemachines/beta_user/sm.py
cr_kyoushi/statemachines/beta_user/sm.smcat
cr_kyoushi/statemachines/beta_user/states.py
cr_kyoushi/statemachines/core/__init__.py
cr_kyoushi/statemachines/core/config.py
cr_kyoushi/statemachines/core/model.py
cr_kyoushi/statemachines/core/selenium.py
cr_kyoushi/statemachines/core/sm.py
cr_kyoushi/statemachines/core/states.py
cr_kyoushi/statemachines/core/transitions.py
cr_kyoushi/statemachines/core/util.py
cr_kyoushi/statemachines/horde_user/__init__.py
cr_kyoushi/statemachines/horde_user/actions.py
cr_kyoushi/statemachines/horde_user/activities.py
cr_kyoushi/statemachines/horde_user/config.py
cr_kyoushi/statemachines/horde_user/context.py
cr_kyoushi/statemachines/horde_user/nav.py
cr_kyoushi/statemachines/horde_user/sm.py
cr_kyoushi/statemachines/horde_user/sm.smcat
cr_kyoushi/statemachines/horde_user/states.py
cr_kyoushi/statemachines/horde_user/wait.py
cr_kyoushi/statemachines/owncloud_user/__init__.py
cr_kyoushi/statemachines/owncloud_user/actions.py
cr_kyoushi/statemachines/owncloud_user/activities.py
cr_kyoushi/statemachines/owncloud_user/config.py
cr_kyoushi/statemachines/owncloud_user/context.py
cr_kyoushi/statemachines/owncloud_user/gather.py
cr_kyoushi/statemachines/owncloud_user/nav.py
cr_kyoushi/statemachines/owncloud_user/sm.py
cr_kyoushi/statemachines/owncloud_user/sm.smcat
kyoushi_statemachines-0.4.1.dist-info/entry_points.txt
kyoushi_statemachines-0.4.1.dist-info/LICENSE
kyoushi_statemachines-0.4.1.dist-info/WHEEL
kyoushi_statemachines-0.4.1.dist-info/METADATA
kyoushi_statemachines-0.4.1.dist-info/RECORD
