Metadata-Version: 2.1
Name: kyoushi-statemachines
Version: 0.4.1
Summary: 
Home-page: https://ait-aecid.github.io/kyoushi-statemachines
License: MIT
Author: Maximilian Frank
Author-email: maximilian.frank@ait.ac.at
Requires-Python: >=3.7,<4.0
Classifier: License :: OSI Approved :: MIT License
Classifier: Programming Language :: Python :: 3
Classifier: Programming Language :: Python :: 3.7
Classifier: Programming Language :: Python :: 3.8
Classifier: Programming Language :: Python :: 3.9
Requires-Dist: Faker (>=5.6.5,<6.0.0)
Requires-Dist: beautifulsoup4 (>=4.9.3,<5.0.0)
Requires-Dist: email-validator (>=1.1.2,<2.0.0)
Requires-Dist: idna (>=2.8,<3.0)
Requires-Dist: kyoushi-simulation (>=0.3.8,<0.4.0)
Requires-Dist: numpy (>=1.19.5,<2.0.0)
Requires-Dist: pwntools (>=4.3.1,<5.0.0)
Requires-Dist: selenium (>=3.141.0,<4.0.0)
Requires-Dist: titlecase (>=2.0.0,<3.0.0)
Requires-Dist: webdriver-manager (>=3.2.2,<4.0.0)
Project-URL: Repository, https://github.com/ait-aecid/kyoushi-statemachines
